padrick/CLIEntryPoint.py
padrick/ConfigParser.py
padrick/__init__.py
padrick/Generators/CLIGeneratorCommands.py
padrick/Generators/GeneratorSettings.py
padrick/Generators/PadrickTemplate.py
padrick/Generators/__init__.py
padrick/Generators/ConstraintsGenerator/ConstraintsGenerator.py
padrick/Generators/ConstraintsGenerator/ConstraintsSpec.py
padrick/Generators/ConstraintsGenerator/__init__.py
padrick/Generators/ConstraintsGenerator/Templates/__init__.py
padrick/Generators/ConstraintsGenerator/Templates/set_case_analysis.sdc.mako
padrick/Generators/DocGenerator/DocGenerator.py
padrick/Generators/DocGenerator/__init__.py
padrick/Generators/DocGenerator/Templates/__init__.py
padrick/Generators/DriverGenerator/DriverGenerator.py
padrick/Generators/DriverGenerator/__init__.py
padrick/Generators/DriverGenerator/Templates/__init__.py
padrick/Generators/DriverGenerator/Templates/bitfield.h
padrick/Generators/DriverGenerator/Templates/driver.c.mako
padrick/Generators/DriverGenerator/Templates/driver.h.mako
padrick/Generators/FuseSoCGenerator/FuseSoCGenerator.py
padrick/Generators/FuseSoCGenerator/FuseSoCGeneratorConfigFileModel.py
padrick/Generators/FuseSoCGenerator/__init__.py
padrick/Generators/RTLGenerator/RTLGenerator.py
padrick/Generators/RTLGenerator/__init__.py
padrick/Generators/RTLGenerator/Templates/Bender.yml.mako
padrick/Generators/RTLGenerator/Templates/FuseSoC.core.mako
padrick/Generators/RTLGenerator/Templates/__init__.py
padrick/Generators/RTLGenerator/Templates/assign.svh.mako
padrick/Generators/RTLGenerator/Templates/ips_list.yml.mako
padrick/Generators/RTLGenerator/Templates/pad_domain.sv.mako
padrick/Generators/RTLGenerator/Templates/pad_multiplexer.sv.mako
padrick/Generators/RTLGenerator/Templates/padframe.sv.mako
padrick/Generators/RTLGenerator/Templates/pads.sv.mako
padrick/Generators/RTLGenerator/Templates/pkg_pad_domain_internals.sv.mako
padrick/Generators/RTLGenerator/Templates/pkg_padframe.sv.mako
padrick-0.3.6.dist-info/AUTHORS.rst
padrick-0.3.6.dist-info/LICENSE.txt
padrick-0.3.6.dist-info/METADATA
padrick-0.3.6.dist-info/WHEEL
padrick-0.3.6.dist-info/entry_points.txt
padrick-0.3.6.dist-info/top_level.txt
padrick-0.3.6.dist-info/RECORD
